[
    {
        "위치코드_시군구": "18034",
        "사고건수": 12,
        "시군구명": "전라남도 목포시"
    },
    {
        "위치코드_시군구": "18044",
        "사고건수": 16,
        "시군구명": "전라남도 여수시"
    },
    {
        "위치코드_시군구": "18054",
        "사고건수": 8,
        "시군구명": "전라남도 순천시"
    },
    {
        "위치코드_시군구": "18084",
        "사고건수": 5,
        "시군구명": "전라남도 고흥군"
    },
    {
        "위치코드_시군구": "18234",
        "사고건수": 6,
        "시군구명": "전라남도 광양시"
    },
    {
        "위치코드_시군구": "46110",
        "사고건수": 781,
        "시군구명": "전라남도 목포시"
    },
    {
        "위치코드_시군구": "46130",
        "사고건수": 833,
        "시군구명": "전라남도 여수시"
    },
    {
        "위치코드_시군구": "46150",
        "사고건수": 632,
        "시군구명": "전라남도 순천시"
    },
    {
        "위치코드_시군구": "46170",
        "사고건수": 204,
        "시군구명": "전라남도 나주시"
    },
    {
        "위치코드_시군구": "46230",
        "사고건수": 299,
        "시군구명": "전라남도 광양시"
    },
    {
        "위치코드_시군구": "46710",
        "사고건수": 205,
        "시군구명": "전라남도 담양군"
    },
    {
        "위치코드_시군구": "46720",
        "사고건수": 102,
        "시군구명": "전라남도 곡성군"
    },
    {
        "위치코드_시군구": "46730",
        "사고건수": 104,
        "시군구명": "전라남도 구례군"
    },
    {
        "위치코드_시군구": "46770",
        "사고건수": 177,
        "시군구명": "전라남도 고흥군"
    },
    {
        "위치코드_시군구": "46780",
        "사고건수": 116,
        "시군구명": "전라남도 보성군"
    },
    {
        "위치코드_시군구": "46790",
        "사고건수": 166,
        "시군구명": "전라남도 화순군"
    },
    {
        "위치코드_시군구": "46800",
        "사고건수": 184,
        "시군구명": "전라남도 장흥군"
    },
    {
        "위치코드_시군구": "46810",
        "사고건수": 144,
        "시군구명": "전라남도 강진군"
    },
    {
        "위치코드_시군구": "46820",
        "사고건수": 174,
        "시군구명": "전라남도 해남군"
    },
    {
        "위치코드_시군구": "46830",
        "사고건수": 164,
        "시군구명": "전라남도 영암군"
    },
    {
        "위치코드_시군구": "46840",
        "사고건수": 187,
        "시군구명": "전라남도 무안군"
    },
    {
        "위치코드_시군구": "46860",
        "사고건수": 91,
        "시군구명": "전라남도 함평군"
    },
    {
        "위치코드_시군구": "46870",
        "사고건수": 157,
        "시군구명": "전라남도 영광군"
    },
    {
        "위치코드_시군구": "46880",
        "사고건수": 138,
        "시군구명": "전라남도 장성군"
    },
    {
        "위치코드_시군구": "46890",
        "사고건수": 175,
        "시군구명": "전라남도 완도군"
    },
    {
        "위치코드_시군구": "46900",
        "사고건수": 129,
        "시군구명": "전라남도 진도군"
    },
    {
        "위치코드_시군구": "46910",
        "사고건수": 54,
        "시군구명": "전라남도 신안군"
    }
]